{
    "1946": {
        "birth": "1009万",
        "death": "",
        "info": ""
    },
    "1947": {
        "birth": "1122万",
        "death": "",
        "info": ""
    },
    "1948": {
        "birth": "1139万",
        "death": "",
        "info": ""
    },
    "1949": {
        "birth": "1275万",
        "death": "",
        "info": ""
    },
    "1950": {
        "birth": "1419万",
        "death": "",
        "info": ""
    },
    "1951": {
        "birth": "1349万",
        "death": "",
        "info": ""
    },
    "1952": {
        "birth": "1622万",
        "death": "",
        "info": ""
    },
    "1953": {
        "birth": "1637万",
        "death": "",
        "info": ""
    },
    "1954": {
        "birth": "2232万",
        "death": "",
        "info": ""
    },
    "1955": {
        "birth": "1965万",
        "death": "",
        "info": ""
    },
    "1956": {
        "birth": "1961万",
        "death": "",
        "info": ""
    },
    "1957": {
        "birth": "2138万",
        "death": "",
        "info": ""
    },
    "1958": {
        "birth": "1889万",
        "death": "",
        "info": ""
    },
    "1959": {
        "birth": "1635万",
        "death": "",
        "info": ""
    },
    "1960": {
        "birth": "1402万",
        "death": "",
        "info": ""
    },
    "1961": {
        "birth": "949万",
        "death": "",
        "info": ""
    },
    "1962": {
        "birth": "2451万",
        "death": "",
        "info": ""
    },
    "1963": {
        "birth": "2934万",
        "death": "",
        "info": ""
    },
    "1964": {
        "birth": "2721万",
        "death": "",
        "info": ""
    },
    "1965": {
        "birth": "2679万",
        "death": "",
        "info": ""
    },
    "1966": {
        "birth": "2554万",
        "death": "",
        "info": ""
    },
    "1967": {
        "birth": "2543万",
        "death": "",
        "info": ""
    },
    "1968": {
        "birth": "2731万",
        "death": "",
        "info": ""
    },
    "1969": {
        "birth": "2690万",
        "death": "",
        "info": ""
    },
    "1970": {
        "birth": "2710万",
        "death": "",
        "info": ""
    },
    "1971": {
        "birth": "2551万",
        "death": "",
        "info": ""
    },
    "1972": {
        "birth": "2550万",
        "death": "",
        "info": ""
    },
    "1973": {
        "birth": "2447万",
        "death": "",
        "info": ""
    },
    "1974": {
        "birth": "2226万",
        "death": "",
        "info": ""
    },
    "1975": {
        "birth": "2102万",
        "death": "",
        "info": ""
    },
    "1976": {
        "birth": "1849万",
        "death": "",
        "info": ""
    },
    "1977": {
        "birth": "1783万",
        "death": "",
        "info": ""
    },
    "1978": {
        "birth": "1733万",
        "death": "",
        "info": ""
    },
    "1979": {
        "birth": "1715万",
        "death": "",
        "info": ""
    },
    "1980": {
        "birth": "1776万",
        "death": "",
        "info": ""
    },
    "1981": {
        "birth": "2064万",
        "death": "",
        "info": ""
    },
    "1982": {
        "birth": "2230万",
        "death": "",
        "info": ""
    },
    "1983": {
        "birth": "2052万",
        "death": "",
        "info": ""
    },
    "1984": {
        "birth": "2050万",
        "death": "",
        "info": ""
    },
    "1985": {
        "birth": "2196万",
        "death": "",
        "info": ""
    },
    "1986": {
        "birth": "2374万",
        "death": "",
        "info": ""
    },
    "1987": {
        "birth": "2508万",
        "death": "",
        "info": ""
    },
    "1988": {
        "birth": "2445万",
        "death": "",
        "info": ""
    },
    "1989": {
        "birth": "2396万",
        "death": "",
        "info": ""
    },
    "1990": {
        "birth": "2374万",
        "death": "",
        "info": ""
    },
    "1991": {
        "birth": "2250万",
        "death": "",
        "info": ""
    },
    "1992": {
        "birth": "2113万",
        "death": "",
        "info": ""
    },
    "1993": {
        "birth": "2120万",
        "death": "",
        "info": ""
    },
    "1994": {
        "birth": "2098万",
        "death": "",
        "info": ""
    },
    "1995": {
        "birth": "2052万",
        "death": "",
        "info": ""
    },
    "1996": {
        "birth": "2057万",
        "death": "",
        "info": ""
    },
    "1997": {
        "birth": "2028万",
        "death": "",
        "info": ""
    },
    "1998": {
        "birth": "1934万",
        "death": "",
        "info": ""
    },
    "1999": {
        "birth": "1827万",
        "death": "",
        "info": ""
    },
    "2000": {
        "birth": "1765万",
        "death": "",
        "info": ""
    },
    "2001": {
        "birth": "1696万",
        "death": "",
        "info": ""
    },
    "2002": {
        "birth": "1641万",
        "death": "",
        "info": ""
    },
    "2003": {
        "birth": "1594万",
        "death": "",
        "info": ""
    },
    "2004": {
        "birth": "1588万",
        "death": "",
        "info": ""
    },
    "2005": {
        "birth": "1612万",
        "death": "",
        "info": ""
    },
    "2006": {
        "birth": "1581万",
        "death": "",
        "info": ""
    },
    "2007": {
        "birth": "1591万",
        "death": "",
        "info": ""
    },
    "2008": {
        "birth": "1604万",
        "death": "",
        "info": ""
    },
    "2009": {
        "birth": "1587万",
        "death": "",
        "info": ""
    },
    "2010": {
        "birth": "1588万",
        "death": "",
        "info": ""
    },
    "2011": {
        "birth": "1600万",
        "death": "",
        "info": ""
    },
    "2012": {
        "birth": "1800万",
        "death": "",
        "info": ""
    },
    "2013": {
        "birth": "1640万",
        "death": "",
        "info": ""
    },
    "2014": {
        "birth": "1687万",
        "death": "",
        "info": ""
    },
    "2015": {
        "birth": "1655万",
        "death": "",
        "info": ""
    },
    "2016": {
        "birth": "1786万",
        "death": "",
        "info": ""
    },
    "2017": {
        "birth": "1723万",
        "death": "",
        "info": ""
    },
    "2018": {
        "birth": "1523万",
        "death": "",
        "info": ""
    },
    "2019": {
        "birth": "1465万",
        "death": "",
        "info": ""
    },
    "2020": {
        "birth": "1200万",
        "death": "",
        "info": ""
    },
    "2021": {
        "birth": "1062万",
        "death": "",
        "info": ""
    },
    "2022": {
        "birth": "956万",
        "death": "",
        "info": ""
    }
}